mdx_include/__init__.py
mdx_include/mdx_include.py
mdx_include/version.py
mdx_include-1.4.2.dist-info/LICENSE
mdx_include-1.4.2.dist-info/METADATA
mdx_include-1.4.2.dist-info/WHEEL
mdx_include-1.4.2.dist-info/top_level.txt
mdx_include-1.4.2.dist-info/RECORD
